[
    {
        "key": "dbln",
        "value": "%7B%2261578574348917%22%3A%22oFPW4sNR%22%2C%22100075836503556%22%3A%22Xx80K8yP%22%2C%22100078903639905%22%3A%22lwqk3dja%22%2C%2261566138525890%22%3A%22XIm9WZ0h%22%7D",
        "domain": "facebook.com",
        "path": "/login/device-based/",
        "hostOnly": false,
        "creation": "2025-08-23T15:22:38.962Z",
        "lastAccessed": "2025-08-23T15:22:38.963Z"
    },
    {
        "key": "datr",
        "value": "R2KKaAt2KE3vcOIGPsE5kvon",
        "domain": "facebook.com",
        "path": "/",
        "hostOnly": false,
        "creation": "2025-08-23T15:22:38.963Z",
        "lastAccessed": "2025-08-23T15:22:38.963Z"
    },
    {
        "key": "sb",
        "value": "SGKKaIVxhvwAlq2nNPWSO31C",
        "domain": "facebook.com",
        "path": "/",
        "hostOnly": false,
        "creation": "2025-08-23T15:22:38.963Z",
        "lastAccessed": "2025-08-23T15:22:38.963Z"
    },
    {
        "key": "ps_l",
        "value": "1",
        "domain": "facebook.com",
        "path": "/",
        "hostOnly": false,
        "creation": "2025-08-23T15:22:38.963Z",
        "lastAccessed": "2025-08-23T15:22:38.963Z"
    },
    {
        "key": "ps_n",
        "value": "1",
        "domain": "facebook.com",
        "path": "/",
        "hostOnly": false,
        "creation": "2025-08-23T15:22:38.963Z",
        "lastAccessed": "2025-08-23T15:22:38.963Z"
    },
    {
        "key": "vpd",
        "value": "v1%3B820x412x2.625",
        "domain": "facebook.com",
        "path": "/",
        "hostOnly": false,
        "creation": "2025-08-23T15:22:38.963Z",
        "lastAccessed": "2025-08-23T15:22:38.963Z"
    },
    {
        "key": "pas",
        "value": "61578574348917%3An7NYRuyKM2%2C100075836503556%3AFj4Gd6VtJT%2C100078903639905%3AlOK5JQu0mK%2C61566138525890%3Aptr9CZwRLw",
        "domain": "facebook.com",
        "path": "/",
        "hostOnly": false,
        "creation": "2025-08-23T15:22:38.963Z",
        "lastAccessed": "2025-08-23T15:22:38.963Z"
    },
    {
        "key": "locale",
        "value": "en_US",
        "domain": "facebook.com",
        "path": "/",
        "hostOnly": false,
        "creation": "2025-08-23T15:22:38.963Z",
        "lastAccessed": "2025-08-23T15:22:38.963Z"
    },
    {
        "key": "m_pixel_ratio",
        "value": "2.625",
        "domain": "facebook.com",
        "path": "/",
        "hostOnly": false,
        "creation": "2025-08-23T15:22:38.963Z",
        "lastAccessed": "2025-08-23T15:22:38.963Z"
    },
    {
        "key": "wd",
        "value": "412x918",
        "domain": "facebook.com",
        "path": "/",
        "hostOnly": false,
        "creation": "2025-08-23T15:22:38.963Z",
        "lastAccessed": "2025-08-23T15:22:38.963Z"
    },
    {
        "key": "c_user",
        "value": "100078903639905",
        "domain": "facebook.com",
        "path": "/",
        "hostOnly": false,
        "creation": "2025-08-23T15:22:38.963Z",
        "lastAccessed": "2025-08-23T15:22:38.963Z"
    },
    {
        "key": "xs",
        "value": "50%3AlGZ_6N3VRc8h_g%3A2%3A1755962547%3A-1%3A-1",
        "domain": "facebook.com",
        "path": "/",
        "hostOnly": false,
        "creation": "2025-08-23T15:22:38.963Z",
        "lastAccessed": "2025-08-23T15:22:38.963Z"
    },
    {
        "key": "fr",
        "value": "0GWAN66ZVPUlbLMDb.AWdgcjfvw4Sghl_9fvwEsTZDx73OwjupnoTqCHU2UXXs9uw4hUQ.BoimJI..AAA.0.0.Boqdy1.AWe1svfCOoMD_xx_RjSyMqj5ItE",
        "domain": "facebook.com",
        "path": "/",
        "hostOnly": false,
        "creation": "2025-08-23T15:22:38.963Z",
        "lastAccessed": "2025-08-23T15:22:38.963Z"
    },
    {
        "key": "fbl_st",
        "value": "101739112%3BT%3A29266042",
        "domain": "facebook.com",
        "path": "/",
        "hostOnly": false,
        "creation": "2025-08-23T15:22:38.963Z",
        "lastAccessed": "2025-08-23T15:22:38.963Z"
    },
    {
        "key": "wl_cbv",
        "value": "v2%3Bclient_version%3A2900%3Btimestamp%3A1755962550",
        "domain": "facebook.com",
        "path": "/",
        "hostOnly": false,
        "creation": "2025-08-23T15:22:38.963Z",
        "lastAccessed": "2025-08-23T15:22:38.963Z"
    }
]
